optimus/__init__.py
optimus/analyzer.py
optimus/cli.py
optimus/properties.py
optimus/results.py
optimus/rules.py
optimus/utils.py
optimus_chem-1.0.0.dist-info/METADATA
optimus_chem-1.0.0.dist-info/WHEEL
optimus_chem-1.0.0.dist-info/entry_points.txt
optimus_chem-1.0.0.dist-info/top_level.txt
optimus_chem-1.0.0.dist-info/RECORD
