Metadata-Version: 2.4
Name: optimus-chem
Version: 1.0.0
Summary: Comprehensive Chemical Analysis Package for Drug Discovery
Home-page: https://github.com/pritampanda15/Optimus_Chemical_Analyzer
Author: Pritam Kumar Panda
Author-email: pritam@stanford.edu
Classifier: Development Status :: 4 - Beta
Classifier: Intended Audience :: Science/Research
Classifier: License :: OSI Approved :: MIT License
Classifier: Operating System :: OS Independent
Classifier: Programming Language :: Python :: 3
Classifier: Programming Language :: Python :: 3.7
Classifier: Programming Language :: Python :: 3.8
Classifier: Programming Language :: Python :: 3.9
Classifier: Programming Language :: Python :: 3.10
Classifier: Programming Language :: Python :: 3.11
Classifier: Topic :: Scientific/Engineering :: Chemistry
Classifier: Topic :: Scientific/Engineering :: Bio-Informatics
Requires-Python: >=3.7
Requires-Dist: rdkit>=2022.3.5
Requires-Dist: numpy>=1.19.0
Requires-Dist: pandas>=1.3.0
Requires-Dist: matplotlib>=3.3.0
Requires-Dist: seaborn>=0.11.0
Requires-Dist: tqdm>=4.62.0
Requires-Dist: click>=8.0.0
Provides-Extra: dev
Requires-Dist: pytest>=6.0; extra == "dev"
Requires-Dist: pytest-cov>=2.0; extra == "dev"
Requires-Dist: black>=21.0; extra == "dev"
Requires-Dist: flake8>=3.8; extra == "dev"
Requires-Dist: mypy>=0.910; extra == "dev"
Provides-Extra: viz
Requires-Dist: plotly>=5.0.0; extra == "viz"
Requires-Dist: bokeh>=2.4.0; extra == "viz"
Dynamic: author
Dynamic: author-email
Dynamic: classifier
Dynamic: description
Dynamic: description-content-type
Dynamic: home-page
Dynamic: provides-extra
Dynamic: requires-dist
Dynamic: requires-python
Dynamic: summary
